{
  "model": "prototype_similarity",
  "n_test_statistics": 8,
  "n_replicates": 200,
  "significance_alpha": 0.05,
  "n_significant": 1,
  "n_significant_fdr": 0,
  "results": [
    {
      "name": "beta_max_run_norm",
      "description": "Linear regression slope of chose_left on the difference in normalized max run length (max_run_norm_b - max_run_norm_a).",
      "t_observed": 0.016447941077551837,
      "null_mean": 0.14624595879794688,
      "null_std": 0.06639121872542532,
      "n_replicates": 200,
      "z_score": -1.9550479749016465,
      "p_value": 0.04975124378109453,
      "p_value_one_sided": 0.9800995024875622,
      "p_value_is_floor": false,
      "significant": true,
      "error": null,
      "code": "# name: beta_max_run_norm\n# description: Linear regression slope of chose_left on the difference in normalized max run length (max_run_norm_b - max_run_norm_a).\n\nimport numpy as np\n\n\ndef test_statistic(df):\n    x = df[\"max_run_norm_b\"] - df[\"max_run_norm_a\"]\n    y = df[\"chose_left\"]\n    if np.var(x) < 1e-8:\n        return 0.0\n    return float(np.cov(x, y)[0, 1] / np.var(x))\n",
      "p_value_fdr": 0.39800995024875624,
      "significant_fdr": false
    },
    {
      "name": "beta_rep_motifs",
      "description": "Linear regression slope of chose_left on the difference in repeating motifs (rep_motifs_b - rep_motifs_a).",
      "t_observed": -0.0020773918448704124,
      "null_mean": -0.019096267714870753,
      "null_std": 0.00962889340928713,
      "n_replicates": 200,
      "z_score": 1.7674799321784502,
      "p_value": 0.10945273631840796,
      "p_value_one_sided": 0.05472636815920398,
      "p_value_is_floor": false,
      "significant": false,
      "error": null,
      "code": "# name: beta_rep_motifs\n# description: Linear regression slope of chose_left on the difference in repeating motifs (rep_motifs_b - rep_motifs_a).\n\nimport numpy as np\n\n\ndef test_statistic(df):\n    x = df[\"rep_motifs_b\"] - df[\"rep_motifs_a\"]\n    y = df[\"chose_left\"]\n    if np.var(x) < 1e-8:\n        return 0.0\n    return float(np.cov(x, y)[0, 1] / np.var(x))\n",
      "p_value_fdr": 0.43781094527363185,
      "significant_fdr": false
    },
    {
      "name": "beta_periodicity",
      "description": "Linear regression slope of chose_left on the difference in periodicity (periodicity_b - periodicity_a).",
      "t_observed": -0.09522763637987994,
      "null_mean": -0.1340715128020785,
      "null_std": 0.034579805423190786,
      "n_replicates": 200,
      "z_score": 1.1233110177117447,
      "p_value": 0.30845771144278605,
      "p_value_one_sided": 0.15422885572139303,
      "p_value_is_floor": false,
      "significant": false,
      "error": null,
      "code": "# name: beta_periodicity\n# description: Linear regression slope of chose_left on the difference in periodicity (periodicity_b - periodicity_a).\n\nimport numpy as np\n\n\ndef test_statistic(df):\n    x = df[\"periodicity_b\"] - df[\"periodicity_a\"]\n    y = df[\"chose_left\"]\n    if np.var(x) < 1e-8:\n        return 0.0\n    return float(np.cov(x, y)[0, 1] / np.var(x))\n",
      "p_value_fdr": 0.6500829187396352,
      "significant_fdr": false
    },
    {
      "name": "high_periodicity_rejection",
      "description": "Mean probability of choosing left when sequence A is highly periodic (>0.6) but sequence B is not (<0.4).",
      "t_observed": 0.5726141078838174,
      "null_mean": 0.6055809128630705,
      "null_std": 0.03937363070276504,
      "n_replicates": 200,
      "z_score": -0.8372813070789016,
      "p_value": 0.4577114427860697,
      "p_value_one_sided": 0.8059701492537313,
      "p_value_is_floor": false,
      "significant": false,
      "error": null,
      "code": "# name: high_periodicity_rejection\n# description: Mean probability of choosing left when sequence A is highly periodic (>0.6) but sequence B is not (<0.4).\n\nimport numpy as np\n\n\ndef test_statistic(df):\n    mask = (df[\"periodicity_a\"] > 0.6) & (df[\"periodicity_b\"] < 0.4)\n    if mask.sum() == 0:\n        return 0.0\n    return float(df[\"chose_left\"][mask].mean())\n",
      "p_value_fdr": 0.6500829187396352,
      "significant_fdr": false
    },
    {
      "name": "imbalance_sensitivity_diff_by_length",
      "description": "Difference in the slope of chose_left on (imbalance_b - imbalance_a) between long sequences (n >= 7) and short sequences (n <= 5).",
      "t_observed": -0.08159281051695988,
      "null_mean": -0.1549584798199336,
      "null_std": 0.09578603419830341,
      "n_replicates": 200,
      "z_score": 0.7659328410140317,
      "p_value": 0.46766169154228854,
      "p_value_one_sided": 0.23383084577114427,
      "p_value_is_floor": false,
      "significant": false,
      "error": null,
      "code": "# name: imbalance_sensitivity_diff_by_length\n# description: Difference in the slope of chose_left on (imbalance_b - imbalance_a) between long sequences (n >= 7) and short sequences (n <= 5).\n\nimport numpy as np\n\n\ndef test_statistic(df):\n    long_mask = (df[\"n_a\"] >= 7) & (df[\"n_b\"] >= 7)\n    short_mask = (df[\"n_a\"] <= 5) & (df[\"n_b\"] <= 5)\n\n    def get_slope(mask):\n        if mask.sum() < 2:\n            return 0.0\n        x = (df[\"imbalance_b\"] - df[\"imbalance_a\"])[mask]\n        y = df[\"chose_left\"][mask]\n        if np.var(x) < 1e-8:\n            return 0.0\n        return float(np.cov(x, y)[0, 1] / np.var(x))\n\n    return get_slope(long_mask) - get_slope(short_mask)\n",
      "p_value_fdr": 0.6500829187396352,
      "significant_fdr": false
    },
    {
      "name": "beta_alt_motifs_matched_palts",
      "description": "Slope of chose_left on (alt_motifs_b - alt_motifs_a) for trials where the absolute difference in p_alts is less than 0.1.",
      "t_observed": -0.046726501823051325,
      "null_mean": -0.025924855170685504,
      "null_std": 0.03349502931425328,
      "n_replicates": 200,
      "z_score": -0.6210368248137048,
      "p_value": 0.48756218905472637,
      "p_value_one_sided": 0.7611940298507462,
      "p_value_is_floor": false,
      "significant": false,
      "error": null,
      "code": "# name: beta_alt_motifs_matched_palts\n# description: Slope of chose_left on (alt_motifs_b - alt_motifs_a) for trials where the absolute difference in p_alts is less than 0.1.\n\nimport numpy as np\n\n\ndef test_statistic(df):\n    mask = abs(df[\"p_alts_a\"] - df[\"p_alts_b\"]) < 0.1\n    if mask.sum() < 2:\n        return 0.0\n    x = (df[\"alt_motifs_b\"] - df[\"alt_motifs_a\"])[mask]\n    y = df[\"chose_left\"][mask]\n    if np.var(x) < 1e-8:\n        return 0.0\n    return float(np.cov(x, y)[0, 1] / np.var(x))\n",
      "p_value_fdr": 0.6500829187396352,
      "significant_fdr": false
    },
    {
      "name": "beta_length_diff",
      "description": "Slope of chose_left on the difference in sequence lengths (n_a - n_b).",
      "t_observed": 0.0099342920288331,
      "null_mean": 0.011009438795179318,
      "null_std": 0.006093417821351285,
      "n_replicates": 200,
      "z_score": -0.17644395934559304,
      "p_value": 0.8955223880597015,
      "p_value_one_sided": 0.5572139303482587,
      "p_value_is_floor": false,
      "significant": false,
      "error": null,
      "code": "# name: beta_length_diff\n# description: Slope of chose_left on the difference in sequence lengths (n_a - n_b).\n\nimport numpy as np\n\n\ndef test_statistic(df):\n    x = df[\"n_a\"] - df[\"n_b\"]\n    y = df[\"chose_left\"]\n    if np.var(x) < 1e-8:\n        return 0.0\n    return float(np.cov(x, y)[0, 1] / np.var(x))\n",
      "p_value_fdr": 0.9253731343283582,
      "significant_fdr": false
    },
    {
      "name": "extreme_max_run_rejection",
      "description": "Mean probability of choosing left when sequence A has a max_run >= 4 and sequence B has max_run < 3.",
      "t_observed": 0.49047619047619045,
      "null_mean": 0.4971190476190476,
      "null_std": 0.03883769792412202,
      "n_replicates": 200,
      "z_score": -0.17104147511099793,
      "p_value": 0.9253731343283582,
      "p_value_one_sided": 0.582089552238806,
      "p_value_is_floor": false,
      "significant": false,
      "error": null,
      "code": "# name: extreme_max_run_rejection\n# description: Mean probability of choosing left when sequence A has a max_run >= 4 and sequence B has max_run < 3.\n\nimport numpy as np\n\n\ndef test_statistic(df):\n    mask = (df[\"max_run_a\"] >= 4) & (df[\"max_run_b\"] < 3)\n    if mask.sum() == 0:\n        return 0.0\n    return float(df[\"chose_left\"][mask].mean())\n",
      "p_value_fdr": 0.9253731343283582,
      "significant_fdr": false
    }
  ]
}